pyaes_util/__init__.py
pyaes_util/aes_util.py
pyaes_util-1.0.0.dist-info/LICENSE
pyaes_util-1.0.0.dist-info/METADATA
pyaes_util-1.0.0.dist-info/WHEEL
pyaes_util-1.0.0.dist-info/top_level.txt
pyaes_util-1.0.0.dist-info/zip-safe
pyaes_util-1.0.0.dist-info/RECORD
