Metadata-Version: 2.1
Name: pyaes_util
Version: 1.0.0
Summary: aes助手
Home-page: https://github.com/buyfakett
Author: buyfakett
Author-email: buyfakett@vip.qq.com
License: MIT
Requires-Python: >=3.6
License-File: LICENSE
Requires-Dist: pycryptodome
